LICENSE
MANIFEST.in
README.md
README.rst
setup.cfg
setup.py
soft_drf/__init__.py
soft_drf.egg-info/PKG-INFO
soft_drf.egg-info/SOURCES.txt
soft_drf.egg-info/dependency_links.txt
soft_drf.egg-info/requires.txt
soft_drf.egg-info/top_level.txt
soft_drf/api/__init__.py
soft_drf/api/mixins/__init__.py
soft_drf/api/routers/__init__.py
soft_drf/api/routers/auth.py
soft_drf/api/routers/simple.py
soft_drf/api/routers/single.py
soft_drf/api/serializers/__init__.py
soft_drf/api/serializers/base.py
soft_drf/api/viewsets/__init__.py
soft_drf/api/viewsets/nested.py
soft_drf/auth/__init__.py
soft_drf/auth/authentication.py
soft_drf/auth/utilities.py
soft_drf/doc/__init__.py
soft_drf/doc/api_docs.py
soft_drf/doc/api_endpoint.py
soft_drf/doc/views.py
soft_drf/routing/__init__.py
soft_drf/routing/autodiscover.py
soft_drf/routing/urls.py
soft_drf/routing/v1/__init__.py
soft_drf/routing/v1/routers.py
soft_drf/routing/v1/urls.py
soft_drf/static/empty.css
soft_drf/static/soft_drf.min.js
soft_drf/static/soft_drf_style.css
soft_drf/templates/api_documentation.html
soft_drf/templates/index.html
soft_drf/utils/__init__.py
soft_drf/utils/middlewares.py