Metadata-Version: 1.1
Name: soft-drf
Version: 0.3.13
Summary: Mixins and templates to do scaffolding with Django Rest Framework project.
Home-page: https://github.com/angellagunas/soft_drf
Author: Ángel Lagunas
Author-email: angel.david.lagunas@gmail.com
License: UNKNOWN
Download-URL: https://github.com/angellagunas/soft_drf/archive/0.3.13.tar.gz
Platform: UNKNOWN
Classifier: Development Status :: 2 - Pre-Alpha
Classifier: Environment :: Web Environment
Classifier: Framework :: Django
Classifier: Intended Audience :: Developers
Classifier: License :: OSI Approved :: Apache Software License
Classifier: Operating System :: OS Independent
Classifier: Programming Language :: Python :: 3.5
Classifier: Programming Language :: Python :: 3.6
Classifier: Topic :: Software Development :: Libraries :: Application Frameworks
Classifier: Topic :: Software Development :: Libraries :: Python Modules
